pentagraph/__init__.py
pentagraph/lib/__init__.py
pentagraph/lib/bot.py
pentagraph/lib/figures.py
pentagraph/lib/graph.py
pentagraph/lib/graphic.py
pentagraph/lib/math.py
pentagraph/tests/__init__.py
pentagraph/tests/test_graph.py
pentagraph-0.0.1b5.dist-info/LICENSE
pentagraph-0.0.1b5.dist-info/METADATA
pentagraph-0.0.1b5.dist-info/WHEEL
pentagraph-0.0.1b5.dist-info/top_level.txt
pentagraph-0.0.1b5.dist-info/RECORD
