Metadata-Version: 2.1
Name: pentagraph
Version: 0.0.1b5
Summary: Graph representation and tools for programming with pentagame
Home-page: https://github.com/Penta-Game/pentagraph
Author: Cobalt
Author-email: chaosthe0rie@pm.me
License: UNKNOWN
Platform: UNKNOWN
Classifier: Programming Language :: Python :: 3
Classifier: License :: OSI Approved :: MIT License
Classifier: Operating System :: OS Independent
Requires-Python: >=3.8
